{
  "id": "day-segment-1-week-2-day-2",
  "segmentId": "segment-1",
  "weekId": "week-segment-1-2",
  "dayNumber": 2,
  "title": "Day 7 — Field Research & Market Exchange",
  "theme": "Discover",
  "durationHours": 4,
  "learningObjectives": [
    "Conduct field interviews (minimum 3, target 5)",
    "Encode interviews in SPIKE Studio Discover mode",
    "Participate in Market Intelligence Exchange",
    "Capture midweek intelligence reflection"
  ],
  "expectedOutputs": [
    "Encoded interviews",
    "Midweek Intelligence Reflection"
  ],
  "portfolioDeliverables": ["portfolio-market-intelligence"],
  "businessPlanIntegration": "bp-chapter-2",
  "presentations": ["presentation-w2-d2-deck-01"],
  "activities": ["activity-w2-d2-field", "activity-w2-d2-exchange"],
  "worksheets": [],
  "assessments": ["assessment-w2-d2"]
}
