{
  "sessions": [
    {
      "id": "session-w3-d5-full",
      "dayId": "day-segment-1-week-3-day-5",
      "sessionNumber": 1,
      "title": "Day 15 — Business Operations Review & 120-Hour Gate",
      "durationMinutes": 240,
      "presentationIds": [
        "presentation-w3-d5-deck-01",
        "presentation-w3-d5-deck-02"
      ],
      "activityIds": [
        "activity-w3-d5-01",
        "activity-w3-d5-02",
        "activity-w3-d5-03"
      ],
      "worksheetIds": [
        "worksheet-w3-d5-01"
      ],
      "assessmentIds": [
        "assessment-w3-d5"
      ],
      "reflectionIds": [
        "reflection-w3-d5"
      ],
      "surveyIds": [
        "survey-w3-d5"
      ]
    }
  ]
}
